rob/__init__.py
rob/base.py
rob/mixins.py
rob/objects.py
rob/tests.py
rob-0.3.0.dist-info/DESCRIPTION.rst
rob-0.3.0.dist-info/METADATA
rob-0.3.0.dist-info/metadata.json
rob-0.3.0.dist-info/RECORD
rob-0.3.0.dist-info/top_level.txt
rob-0.3.0.dist-info/WHEEL
