Metadata-Version: 2.0
Name: rob
Version: 0.3.0
Summary: Make python objects persistent with Redis.
Home-page: http://github.com/relekang/rob
Author: Rolf Erik Lekang
Author-email: UNKNOWN
License: UNKNOWN
Platform: UNKNOWN
Requires-Dist: redis
